README.md
pyproject.toml
setup.cfg
setup.py
baseapp_blocks/__init__.py
baseapp_blocks.egg-info/PKG-INFO
baseapp_blocks.egg-info/SOURCES.txt
baseapp_blocks.egg-info/dependency_links.txt
baseapp_blocks.egg-info/requires.txt
baseapp_blocks.egg-info/top_level.txt
testproject/__init__.py
testproject/graphql.py
testproject/settings.py
testproject/setup.py
testproject/urls.py
testproject/wsgi.py